{
  "n_rows": 24,
  "per_circuit": {
    "adaptec1": {
      "n_macros": 543,
      "n_seeds": 4,
      "baseline": {
        "n": 4,
        "dv_pct_mean": 0.0,
        "dv_pct_std": 0.0,
        "dv_pct_ci95": [
          0.0,
          0.0
        ],
        "dh_pct_mean": 0.0,
        "dh_pct_std": 0.0,
        "dh_pct_ci95": [
          0.0,
          0.0
        ],
        "time_mean": 8.84726470708847
      },
      "cg_strong": {
        "n": 4,
        "dv_pct_mean": -6.099910138065003,
        "dv_pct_std": 0.6021697165205371,
        "dv_pct_ci95": [
          -6.7399354781943694,
          -5.611872810120427
        ],
        "dh_pct_mean": 46.493731979280376,
        "dh_pct_std": 73.29697874892311,
        "dh_pct_ci95": [
          -3.767930588374636,
          128.61595410929317
        ],
        "time_mean": 9.108900785446167
      },
      "vsr_post": {
        "n": 4,
        "dv_pct_mean": -35.425472293483,
        "dv_pct_std": 1.8164529668176077,
        "dv_pct_ci95": [
          -37.05860121493107,
          -33.72201843793682
        ],
        "dh_pct_mean": 2.1285396528543146,
        "dh_pct_std": 23.72868063128637,
        "dh_pct_ci95": [
          -15.209429049233911,
          28.910927609058476
        ],
        "time_mean": 1.558975338935852
      },
      "repaint_bin": {
        "n": 4,
        "dv_pct_mean": 128.22620073389314,
        "dv_pct_std": 16.54371122896002,
        "dv_pct_ci95": [
          109.42595680309984,
          141.33915500530446
        ],
        "dh_pct_mean": -11.33969296843151,
        "dh_pct_std": 10.276476135582794,
        "dh_pct_ci95": [
          -18.889438410389896,
          0.6855394739532481
        ],
        "time_mean": 0.4880855083465576
      },
      "vsr_intra": {
        "n": 4,
        "dv_pct_mean": 3.2211628595078476,
        "dv_pct_std": 0.5584949110102846,
        "dv_pct_ci95": [
          2.681672735845434,
          3.760652983170261
        ],
        "dh_pct_mean": 0.1765325980287733,
        "dh_pct_std": 6.458877797150614,
        "dh_pct_ci95": [
          -4.419728580696164,
          7.444086019889079
        ],
        "time_mean": 0.46096962690353394
      },
      "cd_std": {
        "n": 4,
        "dv_pct_mean": -26.197231943396293,
        "dv_pct_std": 7.346096146871025,
        "dv_pct_ci95": [
          -32.61628405176239,
          -17.97097393296724
        ],
        "dh_pct_mean": 184.93514096047466,
        "dh_pct_std": 115.92509097513113,
        "dh_pct_ci95": [
          84.30474181901816,
          298.7219006025518
        ],
        "time_mean": 7.579493224620819
      },
      "cd_sched": {
        "n": 4,
        "dv_pct_mean": -14.971166914574516,
        "dv_pct_std": 11.543679138232587,
        "dv_pct_ci95": [
          -25.12794320655575,
          -3.808049924505265
        ],
        "dh_pct_mean": 160.93754313390974,
        "dh_pct_std": 65.08175959391203,
        "dh_pct_ci95": [
          101.90153861442988,
          234.88680137416037
        ],
        "time_mean": 16.628419160842896
      }
    },
    "adaptec2": {
      "n_macros": 566,
      "n_seeds": 4,
      "baseline": {
        "n": 4,
        "dv_pct_mean": 0.0,
        "dv_pct_std": 0.0,
        "dv_pct_ci95": [
          0.0,
          0.0
        ],
        "dh_pct_mean": 0.0,
        "dh_pct_std": 0.0,
        "dh_pct_ci95": [
          0.0,
          0.0
        ],
        "time_mean": 9.130977511405945
      },
      "cg_strong": {
        "n": 4,
        "dv_pct_mean": -4.929406089783892,
        "dv_pct_std": 6.628950576572966,
        "dv_pct_ci95": [
          -11.713460443211055,
          1.1174526363165367
        ],
        "dh_pct_mean": 13.765699520305505,
        "dh_pct_std": 8.483986541592,
        "dh_pct_ci95": [
          5.843638684986242,
          21.344404858390384
        ],
        "time_mean": 9.470030546188354
      },
      "vsr_post": {
        "n": 4,
        "dv_pct_mean": -57.03769237477213,
        "dv_pct_std": 5.296920444319527,
        "dv_pct_ci95": [
          -61.125860814116564,
          -51.291659202539705
        ],
        "dh_pct_mean": 7.798256161007458,
        "dh_pct_std": 11.399610907570727,
        "dh_pct_ci95": [
          -2.847938541995764,
          20.549888602196525
        ],
        "time_mean": 1.7431625127792358
      },
      "repaint_bin": {
        "n": 4,
        "dv_pct_mean": 19.316539801126634,
        "dv_pct_std": 12.104157952344963,
        "dv_pct_ci95": [
          5.900841915514061,
          29.716490630017628
        ],
        "dh_pct_mean": -32.341637274211536,
        "dh_pct_std": 8.05978793349037,
        "dh_pct_ci95": [
          -39.841443032351606,
          -23.165112555328463
        ],
        "time_mean": 0.48631876707077026
      },
      "vsr_intra": {
        "n": 4,
        "dv_pct_mean": 1.181896660629827,
        "dv_pct_std": 0.11127064797013396,
        "dv_pct_ci95": [
          1.0854878053800694,
          1.3031746842347378
        ],
        "dh_pct_mean": -2.536149327883268,
        "dh_pct_std": 0.22625369941085952,
        "dh_pct_ci95": [
          -2.6878572385305697,
          -2.272097458300479
        ],
        "time_mean": 0.4702666997909546
      },
      "cd_std": {
        "n": 4,
        "dv_pct_mean": -43.52643716238754,
        "dv_pct_std": 3.588965272899911,
        "dv_pct_ci95": [
          -46.783509375143495,
          -39.846011712682525
        ],
        "dh_pct_mean": 98.96320441813704,
        "dh_pct_std": 19.787424836477438,
        "dh_pct_ci95": [
          79.36583431656686,
          118.56057451970722
        ],
        "time_mean": 7.628166615962982
      },
      "cd_sched": {
        "n": 4,
        "dv_pct_mean": -51.079398520516364,
        "dv_pct_std": 11.742874696985243,
        "dv_pct_ci95": [
          -64.46428754628437,
          -40.544603361441304
        ],
        "dh_pct_mean": 229.9555649012752,
        "dh_pct_std": 69.86423572894351,
        "dh_pct_ci95": [
          177.23360658520465,
          307.7039705986412
        ],
        "time_mean": 16.964818239212036
      }
    },
    "adaptec3": {
      "n_macros": 723,
      "n_seeds": 4,
      "baseline": {
        "n": 4,
        "dv_pct_mean": 0.0,
        "dv_pct_std": 0.0,
        "dv_pct_ci95": [
          0.0,
          0.0
        ],
        "dh_pct_mean": 0.0,
        "dh_pct_std": 0.0,
        "dh_pct_ci95": [
          0.0,
          0.0
        ],
        "time_mean": 9.245018541812897
      },
      "cg_strong": {
        "n": 4,
        "dv_pct_mean": 4.04744747027379,
        "dv_pct_std": 6.2620083935908655,
        "dv_pct_ci95": [
          -2.036595240238296,
          10.131490180785875
        ],
        "dh_pct_mean": 9.473756663532766,
        "dh_pct_std": 11.526997501682388,
        "dh_pct_ci95": [
          -1.123100011746819,
          19.726482707911497
        ],
        "time_mean": 9.362172544002533
      },
      "vsr_post": {
        "n": 4,
        "dv_pct_mean": -53.46908742996994,
        "dv_pct_std": 2.65486526779528,
        "dv_pct_ci95": [
          -56.412038818302705,
          -51.51032790765712
        ],
        "dh_pct_mean": 29.785524701552596,
        "dh_pct_std": 5.016466963756428,
        "dh_pct_ci95": [
          24.979614504480125,
          34.59143489862507
        ],
        "time_mean": 1.9831820726394653
      },
      "repaint_bin": {
        "n": 4,
        "dv_pct_mean": 139.33221152206772,
        "dv_pct_std": 11.979329469316323,
        "dv_pct_ci95": [
          125.8430654535728,
          147.93441147166786
        ],
        "dh_pct_mean": -65.37760309652512,
        "dh_pct_std": 4.375914476563182,
        "dh_pct_ci95": [
          -69.75017312435577,
          -61.640759485877595
        ],
        "time_mean": 0.5038579106330872
      },
      "vsr_intra": {
        "n": 4,
        "dv_pct_mean": 0.16341324808014407,
        "dv_pct_std": 0.18193014199554286,
        "dv_pct_ci95": [
          -0.010759932787495232,
          0.33758642894778335
        ],
        "dh_pct_mean": -1.8786372268710008,
        "dh_pct_std": 11.501521164897003,
        "dh_pct_ci95": [
          -12.184041148862544,
          8.967099339795917
        ],
        "time_mean": 0.4564476013183594
      },
      "cd_std": {
        "n": 4,
        "dv_pct_mean": 0.6746372846206479,
        "dv_pct_std": 7.455360018278985,
        "dv_pct_ci95": [
          -6.778604763832783,
          8.127879333074079
        ],
        "dh_pct_mean": 108.0568525789043,
        "dh_pct_std": 44.79892618767126,
        "dh_pct_ci95": [
          69.56946899676467,
          158.49456014496658
        ],
        "time_mean": 7.709301710128784
      },
      "cd_sched": {
        "n": 4,
        "dv_pct_mean": -22.48469061658225,
        "dv_pct_std": 15.704531914038293,
        "dv_pct_ci95": [
          -36.59363533746995,
          -6.39440338085378
        ],
        "dh_pct_mean": 270.3119737641995,
        "dh_pct_std": 188.75401255503047,
        "dh_pct_ci95": [
          81.5908448271305,
          459.0331027012684
        ],
        "time_mean": 17.04305136203766
      }
    },
    "adaptec4": {
      "n_macros": 1329,
      "n_seeds": 4,
      "baseline": {
        "n": 4,
        "dv_pct_mean": 0.0,
        "dv_pct_std": 0.0,
        "dv_pct_ci95": [
          0.0,
          0.0
        ],
        "dh_pct_mean": 0.0,
        "dh_pct_std": 0.0,
        "dh_pct_ci95": [
          0.0,
          0.0
        ],
        "time_mean": 9.432564496994019
      },
      "cg_strong": {
        "n": 4,
        "dv_pct_mean": -2.1298224320775825,
        "dv_pct_std": 5.7565985598299365,
        "dv_pct_ci95": [
          -6.496730980805488,
          4.297605174808973
        ],
        "dh_pct_mean": 0.7531003301686304,
        "dh_pct_std": 4.912168436345493,
        "dh_pct_ci95": [
          -4.847389679305351,
          4.4135741468441045
        ],
        "time_mean": 9.499541759490967
      },
      "vsr_post": {
        "n": 4,
        "dv_pct_mean": -57.36535529217672,
        "dv_pct_std": 3.0381509691584094,
        "dv_pct_ci95": [
          -59.66732816069198,
          -53.84088461755466
        ],
        "dh_pct_mean": -10.13173600429179,
        "dh_pct_std": 2.380445450719816,
        "dh_pct_ci95": [
          -12.434289497985928,
          -7.8291825105976525
        ],
        "time_mean": 3.921378791332245
      },
      "repaint_bin": {
        "n": 4,
        "dv_pct_mean": 207.77681669334805,
        "dv_pct_std": 29.499481885198545,
        "dv_pct_ci95": [
          180.86252635801756,
          235.79181714502397
        ],
        "dh_pct_mean": -65.3341844525221,
        "dh_pct_std": 1.515825100521705,
        "dh_pct_ci95": [
          -66.83207798684043,
          -63.83629091820376
        ],
        "time_mean": 0.4664771556854248
      },
      "vsr_intra": {
        "n": 4,
        "dv_pct_mean": 6.200812641661398,
        "dv_pct_std": 2.547134993450352,
        "dv_pct_ci95": [
          3.824952350246804,
          9.070362182618535
        ],
        "dh_pct_mean": -6.609687275079843,
        "dh_pct_std": 1.1257620387137264,
        "dh_pct_ci95": [
          -7.547154656852269,
          -5.446786005448644
        ],
        "time_mean": 0.44211775064468384
      },
      "cd_std": {
        "n": 4,
        "dv_pct_mean": -28.758037879152372,
        "dv_pct_std": 5.67877716242355,
        "dv_pct_ci95": [
          -34.53843813205941,
          -23.990030800240987
        ],
        "dh_pct_mean": 85.81669765925699,
        "dh_pct_std": 11.82592644082645,
        "dh_pct_ci95": [
          73.36564960423675,
          96.1528410339769
        ],
        "time_mean": 7.63360857963562
      },
      "cd_sched": {
        "n": 4,
        "dv_pct_mean": -29.044441168905458,
        "dv_pct_std": 8.321623795757079,
        "dv_pct_ci95": [
          -37.34623696128654,
          -20.742645376524372
        ],
        "dh_pct_mean": 90.02492523090342,
        "dh_pct_std": 22.736760093359123,
        "dh_pct_ci95": [
          67.32474002164116,
          112.72511044016566
        ],
        "time_mean": 16.76556944847107
      }
    },
    "bigblue1": {
      "n_macros": 560,
      "n_seeds": 4,
      "baseline": {
        "n": 4,
        "dv_pct_mean": 0.0,
        "dv_pct_std": 0.0,
        "dv_pct_ci95": [
          0.0,
          0.0
        ],
        "dh_pct_mean": 0.0,
        "dh_pct_std": 0.0,
        "dh_pct_ci95": [
          0.0,
          0.0
        ],
        "time_mean": 8.807733118534088
      },
      "cg_strong": {
        "n": 4,
        "dv_pct_mean": 3.7213213926112676,
        "dv_pct_std": 9.751092046605512,
        "dv_pct_ci95": [
          -4.6882734467170435,
          13.309349738886723
        ],
        "dh_pct_mean": 9.721128072133228,
        "dh_pct_std": 8.386608870203707,
        "dh_pct_ci95": [
          1.4612569053142064,
          17.980999238952247
        ],
        "time_mean": 8.911279797554016
      },
      "vsr_post": {
        "n": 4,
        "dv_pct_mean": -24.151347901851153,
        "dv_pct_std": 9.673241347932755,
        "dv_pct_ci95": [
          -34.9677039991993,
          -16.114995579334597
        ],
        "dh_pct_mean": -67.06950088653687,
        "dh_pct_std": 12.056660980441238,
        "dh_pct_ci95": [
          -77.5515456533121,
          -53.807694160042004
        ],
        "time_mean": 1.3726662397384644
      },
      "repaint_bin": {
        "n": 4,
        "dv_pct_mean": 189.4877687128871,
        "dv_pct_std": 39.69560263256283,
        "dv_pct_ci95": [
          158.7147636945332,
          234.51768646021492
        ],
        "dh_pct_mean": -54.507600133490556,
        "dh_pct_std": 8.109822177379721,
        "dh_pct_ci95": [
          -62.16106745123925,
          -46.85413281574186
        ],
        "time_mean": 0.4976256489753723
      },
      "vsr_intra": {
        "n": 4,
        "dv_pct_mean": 1.373607655386087,
        "dv_pct_std": 0.5127398624660366,
        "dv_pct_ci95": [
          0.8344386720055472,
          1.7932745474859066
        ],
        "dh_pct_mean": 2.669764790738326,
        "dh_pct_std": 4.25485774259891,
        "dh_pct_ci95": [
          -1.5369464221460638,
          6.876476003622717
        ],
        "time_mean": 0.45488178730010986
      },
      "cd_std": {
        "n": 4,
        "dv_pct_mean": -14.227329132665595,
        "dv_pct_std": 5.884251051428238,
        "dv_pct_ci95": [
          -19.820323238200743,
          -7.904027140895562
        ],
        "dh_pct_mean": 81.59960077858163,
        "dh_pct_std": 30.472033048935895,
        "dh_pct_ci95": [
          55.37552439219503,
          112.02336482482254
        ],
        "time_mean": 7.564705312252045
      },
      "cd_sched": {
        "n": 4,
        "dv_pct_mean": -13.106755853387625,
        "dv_pct_std": 7.867788462079088,
        "dv_pct_ci95": [
          -21.810388084517044,
          -5.797206854110701
        ],
        "dh_pct_mean": 207.81222289077863,
        "dh_pct_std": 69.3975568482637,
        "dh_pct_ci95": [
          144.5684918392189,
          271.36936733394
        ],
        "time_mean": 16.093946397304535
      }
    },
    "bigblue3": {
      "n_macros": 1298,
      "n_seeds": 4,
      "baseline": {
        "n": 4,
        "dv_pct_mean": 0.0,
        "dv_pct_std": 0.0,
        "dv_pct_ci95": [
          0.0,
          0.0
        ],
        "dh_pct_mean": 0.0,
        "dh_pct_std": 0.0,
        "dh_pct_ci95": [
          0.0,
          0.0
        ],
        "time_mean": 9.18511176109314
      },
      "cg_strong": {
        "n": 4,
        "dv_pct_mean": 11.125305704654956,
        "dv_pct_std": 22.351767788365592,
        "dv_pct_ci95": [
          -11.181137137672735,
          33.43174854698265
        ],
        "dh_pct_mean": 11.14156957767964,
        "dh_pct_std": 4.62280157610293,
        "dh_pct_ci95": [
          6.596165101812215,
          15.188213618226014
        ],
        "time_mean": 9.410229086875916
      },
      "vsr_post": {
        "n": 4,
        "dv_pct_mean": -77.28609139215737,
        "dv_pct_std": 3.093711976015295,
        "dv_pct_ci95": [
          -80.4350086926089,
          -74.03541624121227
        ],
        "dh_pct_mean": 14.968369543629933,
        "dh_pct_std": 1.7929172904620243,
        "dh_pct_ci95": [
          13.392404965158361,
          16.892936065887238
        ],
        "time_mean": 3.400284230709076
      },
      "repaint_bin": {
        "n": 4,
        "dv_pct_mean": -41.106662024862985,
        "dv_pct_std": 13.787700688413572,
        "dv_pct_ci95": [
          -53.45639894381854,
          -28.08497393489917
        ],
        "dh_pct_mean": -63.25479699407056,
        "dh_pct_std": 2.2320372748665713,
        "dh_pct_ci95": [
          -65.63048504173602,
          -61.460711530802335
        ],
        "time_mean": 0.46935850381851196
      },
      "vsr_intra": {
        "n": 4,
        "dv_pct_mean": -4.131294864673155,
        "dv_pct_std": 2.5735193731337906,
        "dv_pct_ci95": [
          -6.210501251653412,
          -1.2237308119347021
        ],
        "dh_pct_mean": -30.293960800577857,
        "dh_pct_std": 5.377983257010672,
        "dh_pct_ci95": [
          -35.36676591297037,
          -25.22115568818534
        ],
        "time_mean": 0.44494783878326416
      },
      "cd_std": {
        "n": 4,
        "dv_pct_mean": -18.966670120314898,
        "dv_pct_std": 21.123063004373865,
        "dv_pct_ci95": [
          -39.36303878988025,
          -0.3177790895821073
        ],
        "dh_pct_mean": 71.5733903480149,
        "dh_pct_std": 13.617722432325335,
        "dh_pct_ci95": [
          59.19782858345053,
          86.38143004544568
        ],
        "time_mean": 7.742422521114349
      },
      "cd_sched": {
        "n": 4,
        "dv_pct_mean": -50.680857897752404,
        "dv_pct_std": 14.649910848468776,
        "dv_pct_ci95": [
          -63.38370355451802,
          -36.20488645648117
        ],
        "dh_pct_mean": 128.27264786610965,
        "dh_pct_std": 158.162822102414,
        "dh_pct_ci95": [
          17.025663600112356,
          304.12471880098576
        ],
        "time_mean": 16.908351242542267
      }
    }
  },
  "cross_circuit_medians": {
    "baseline": {
      "n_circuits": 6,
      "dv_median": 0.0,
      "dv_mean": 0.0,
      "dh_median": 0.0,
      "dh_mean": 0.0
    },
    "cg_strong": {
      "n_circuits": 6,
      "dv_median": 0.7957494802668426,
      "dv_mean": 0.9558226512689226,
      "dh_median": 10.431348824906433,
      "dh_mean": 15.224831023850024
    },
    "vsr_post": {
      "n_circuits": 6,
      "dv_median": -55.25338990237103,
      "dv_mean": -50.78917444740172,
      "dh_median": 4.9633979069308864,
      "dh_mean": -3.75342447196406
    },
    "repaint_bin": {
      "n_circuits": 6,
      "dv_median": 133.77920612798044,
      "dv_mean": 107.17214590640994,
      "dh_median": -58.88119856378056,
      "dh_mean": -48.69258581987523
    },
    "vsr_intra": {
      "n_circuits": 6,
      "dv_median": 1.277752158007957,
      "dv_mean": 1.3349330334320249,
      "dh_median": -2.2073932773771343,
      "dh_mean": -6.412022873607478
    },
    "cd_std": {
      "n_circuits": 6,
      "dv_median": -22.581951031855596,
      "dv_mean": -21.833511492216008,
      "dh_median": 92.389951038697,
      "dh_mean": 105.15748112389491
    },
    "cd_sched": {
      "n_circuits": 6,
      "dv_median": -25.764565892743853,
      "dv_mean": -30.227885161953104,
      "dh_median": 184.37488301234418,
      "dh_mean": 181.2191462978627
    }
  },
  "strict_pareto": {
    "baseline": {
      "strict": 0,
      "n": 24
    },
    "cg_strong": {
      "strict": 3,
      "n": 24
    },
    "vsr_post": {
      "strict": 12,
      "n": 24
    },
    "repaint_bin": {
      "strict": 5,
      "n": 24
    },
    "vsr_intra": {
      "strict": 4,
      "n": 24
    },
    "cd_std": {
      "strict": 0,
      "n": 24
    },
    "cd_sched": {
      "strict": 0,
      "n": 24
    }
  },
  "wilcoxon": {
    "vsr_post_vs_cd_std": {
      "n": 24,
      "dv": {
        "W": 0,
        "p": 1.8215297148849174e-05
      },
      "dh": {
        "W": 0,
        "p": 1.8215297148849174e-05
      }
    },
    "vsr_post_vs_cd_sched": {
      "n": 24,
      "dv": {
        "W": 8.0,
        "p": 4.9676698643086326e-05
      },
      "dh": {
        "W": 0,
        "p": 1.8215297148849174e-05
      }
    },
    "vsr_post_vs_cg_strong": {
      "n": 24,
      "dv": {
        "W": 0,
        "p": 1.8215297148849174e-05
      },
      "dh": {
        "W": 89.0,
        "p": 0.08135857180414474
      }
    },
    "vsr_post_vs_repaint_bin": {
      "n": 24,
      "dv": {
        "W": 0,
        "p": 1.8215297148849174e-05
      },
      "dh": {
        "W": 19.0,
        "p": 0.0001819396751698843
      }
    },
    "vsr_post_vs_vsr_intra": {
      "n": 24,
      "dv": {
        "W": 0,
        "p": 1.8215297148849174e-05
      },
      "dh": {
        "W": 127.0,
        "p": 0.5110890641174399
      }
    },
    "vsr_intra_vs_cd_std": {
      "n": 24,
      "dv": {
        "W": 19.0,
        "p": 0.0001819396751698843
      },
      "dh": {
        "W": 0,
        "p": 1.8215297148849174e-05
      }
    },
    "vsr_intra_vs_cg_strong": {
      "n": 24,
      "dv": {
        "W": 106.0,
        "p": 0.20870191067235688
      },
      "dh": {
        "W": 11.0,
        "p": 7.144292229011029e-05
      }
    },
    "vsr_intra_vs_repaint_bin": {
      "n": 24,
      "dv": {
        "W": 23.0,
        "p": 0.00028499390185410256
      },
      "dh": {
        "W": 0,
        "p": 1.8215297148849174e-05
      }
    }
  }
}