[
  {
    "circuit": "adaptec1",
    "n_macros": 543,
    "seed": 42,
    "t_sample": 9.276025295257568,
    "baseline_violations": 19293,
    "baseline_overlap": 19150,
    "baseline_boundary": 143,
    "baseline_hpwl": 96.8779525756836,
    "n_offending": 543,
    "hand_violations": 12905,
    "hand_hpwl": 119.45137786865234,
    "t_hand": 1.7670269012451172,
    "neural_violations": null,
    "neural_hpwl": null,
    "t_neural": null,
    "hand_improvement": 33.11045456901467
  },
  {
    "circuit": "adaptec1",
    "n_macros": 543,
    "seed": 123,
    "t_sample": 8.518006801605225,
    "baseline_violations": 21332,
    "baseline_overlap": 21173,
    "baseline_boundary": 159,
    "baseline_hpwl": 96.38492584228516,
    "n_offending": 543,
    "hand_violations": 13212,
    "hand_hpwl": 147.35934448242188,
    "t_hand": 4.065575838088989,
    "neural_violations": null,
    "neural_hpwl": null,
    "t_neural": null,
    "hand_improvement": 38.06487905494093
  },
  {
    "circuit": "adaptec1",
    "n_macros": 543,
    "seed": 300,
    "t_sample": 8.61437702178955,
    "baseline_violations": 19264,
    "baseline_overlap": 19133,
    "baseline_boundary": 131,
    "baseline_hpwl": 118.45597839355469,
    "n_offending": 543,
    "hand_violations": 12286,
    "hand_hpwl": 111.3215560913086,
    "t_hand": 1.5086307525634766,
    "neural_violations": null,
    "neural_hpwl": null,
    "t_neural": null,
    "hand_improvement": 36.22300664451827
  },
  {
    "circuit": "adaptec2",
    "n_macros": 566,
    "seed": 42,
    "t_sample": 8.522653818130493,
    "baseline_violations": 35859,
    "baseline_overlap": 35322,
    "baseline_boundary": 537,
    "baseline_hpwl": 16979.736328125,
    "n_offending": 566,
    "hand_violations": 20269,
    "hand_hpwl": 20997.43359375,
    "t_hand": 2.0767154693603516,
    "neural_violations": null,
    "neural_hpwl": null,
    "t_neural": null,
    "hand_improvement": 43.475835912881
  },
  {
    "circuit": "adaptec2",
    "n_macros": 566,
    "seed": 123,
    "t_sample": 8.705683708190918,
    "baseline_violations": 32521,
    "baseline_overlap": 31957,
    "baseline_boundary": 564,
    "baseline_hpwl": 16935.17578125,
    "n_offending": 566,
    "hand_violations": 16946,
    "hand_hpwl": 19512.39453125,
    "t_hand": 1.491119146347046,
    "neural_violations": null,
    "neural_hpwl": null,
    "t_neural": null,
    "hand_improvement": 47.89213123827681
  },
  {
    "circuit": "adaptec2",
    "n_macros": 566,
    "seed": 300,
    "t_sample": 8.709957599639893,
    "baseline_violations": 32935,
    "baseline_overlap": 32377,
    "baseline_boundary": 558,
    "baseline_hpwl": 17158.36328125,
    "n_offending": 566,
    "hand_violations": 16941,
    "hand_hpwl": 21317.234375,
    "t_hand": 1.7107553482055664,
    "neural_violations": null,
    "neural_hpwl": null,
    "t_neural": null,
    "hand_improvement": 48.56231972066191
  },
  {
    "circuit": "adaptec3",
    "n_macros": 723,
    "seed": 42,
    "t_sample": 9.49241042137146,
    "baseline_violations": 40748,
    "baseline_overlap": 40026,
    "baseline_boundary": 722,
    "baseline_hpwl": 44458.2265625,
    "n_offending": 723,
    "hand_violations": 17745,
    "hand_hpwl": 53492.6484375,
    "t_hand": 2.6172378063201904,
    "neural_violations": null,
    "neural_hpwl": null,
    "t_neural": null,
    "hand_improvement": 56.45185039756553
  },
  {
    "circuit": "adaptec3",
    "n_macros": 723,
    "seed": 123,
    "t_sample": 8.654103517532349,
    "baseline_violations": 40921,
    "baseline_overlap": 40205,
    "baseline_boundary": 716,
    "baseline_hpwl": 40372.796875,
    "n_offending": 723,
    "hand_violations": 18697,
    "hand_hpwl": 51860.7890625,
    "t_hand": 1.5233263969421387,
    "neural_violations": null,
    "neural_hpwl": null,
    "t_neural": null,
    "hand_improvement": 54.30952322768261
  },
  {
    "circuit": "adaptec3",
    "n_macros": 723,
    "seed": 300,
    "t_sample": 8.805174827575684,
    "baseline_violations": 37302,
    "baseline_overlap": 36586,
    "baseline_boundary": 716,
    "baseline_hpwl": 45827.94921875,
    "n_offending": 723,
    "hand_violations": 19189,
    "hand_hpwl": 50465.4921875,
    "t_hand": 1.776726245880127,
    "neural_violations": null,
    "neural_hpwl": null,
    "t_neural": null,
    "hand_improvement": 48.55771808482119
  },
  {
    "circuit": "adaptec4",
    "n_macros": 1329,
    "seed": 42,
    "t_sample": 8.574747085571289,
    "baseline_violations": 110491,
    "baseline_overlap": 109688,
    "baseline_boundary": 803,
    "baseline_hpwl": 61447.44921875,
    "n_offending": 1329,
    "hand_violations": 43535,
    "hand_hpwl": 52285.40234375,
    "t_hand": 8.315392255783081,
    "neural_violations": null,
    "neural_hpwl": null,
    "t_neural": null,
    "hand_improvement": 60.598600791014654
  },
  {
    "circuit": "adaptec4",
    "n_macros": 1329,
    "seed": 123,
    "t_sample": 8.522222757339478,
    "baseline_violations": 106768,
    "baseline_overlap": 105912,
    "baseline_boundary": 856,
    "baseline_hpwl": 63948.55078125,
    "n_offending": 1329,
    "hand_violations": 43951,
    "hand_hpwl": 53385.7890625,
    "t_hand": 4.713113307952881,
    "neural_violations": null,
    "neural_hpwl": null,
    "t_neural": null,
    "hand_improvement": 58.835044208002394
  },
  {
    "circuit": "adaptec4",
    "n_macros": 1329,
    "seed": 300,
    "t_sample": 8.725704431533813,
    "baseline_violations": 106963,
    "baseline_overlap": 106055,
    "baseline_boundary": 908,
    "baseline_hpwl": 59198.7578125,
    "n_offending": 1329,
    "hand_violations": 43700,
    "hand_hpwl": 55920.0078125,
    "t_hand": 7.2977635860443115,
    "neural_violations": null,
    "neural_hpwl": null,
    "t_neural": null,
    "hand_improvement": 59.14475098865963
  },
  {
    "circuit": "bigblue1",
    "n_macros": 560,
    "seed": 42,
    "t_sample": 8.103681325912476,
    "baseline_violations": 11347,
    "baseline_overlap": 11240,
    "baseline_boundary": 107,
    "baseline_hpwl": 11.745893478393555,
    "n_offending": 560,
    "hand_violations": 8765,
    "hand_hpwl": 3.3131837844848633,
    "t_hand": 1.0786969661712646,
    "neural_violations": null,
    "neural_hpwl": null,
    "t_neural": null,
    "hand_improvement": 22.75491319291443
  },
  {
    "circuit": "bigblue1",
    "n_macros": 560,
    "seed": 123,
    "t_sample": 8.292213916778564,
    "baseline_violations": 10416,
    "baseline_overlap": 10310,
    "baseline_boundary": 106,
    "baseline_hpwl": 15.7106351852417,
    "n_offending": 560,
    "hand_violations": 8968,
    "hand_hpwl": 3.021653175354004,
    "t_hand": 1.1111557483673096,
    "neural_violations": null,
    "neural_hpwl": null,
    "t_neural": null,
    "hand_improvement": 13.90168970814132
  },
  {
    "circuit": "bigblue1",
    "n_macros": 560,
    "seed": 300,
    "t_sample": 8.265430688858032,
    "baseline_violations": 11799,
    "baseline_overlap": 11693,
    "baseline_boundary": 106,
    "baseline_hpwl": 10.463732719421387,
    "n_offending": 560,
    "hand_violations": 7084,
    "hand_hpwl": 3.358262538909912,
    "t_hand": 1.0298030376434326,
    "neural_violations": null,
    "neural_hpwl": null,
    "t_neural": null,
    "hand_improvement": 39.96101364522417
  },
  {
    "circuit": "bigblue3",
    "n_macros": 1298,
    "seed": 42,
    "t_sample": 9.206281900405884,
    "baseline_violations": 205735,
    "baseline_overlap": 204437,
    "baseline_boundary": 1298,
    "baseline_hpwl": 101432.5390625,
    "n_offending": 1298,
    "hand_violations": 41114,
    "hand_hpwl": 117523.4921875,
    "t_hand": 3.116804838180542,
    "neural_violations": null,
    "neural_hpwl": null,
    "t_neural": null,
    "hand_improvement": 80.01604005152258
  },
  {
    "circuit": "bigblue3",
    "n_macros": 1298,
    "seed": 123,
    "t_sample": 10.372862100601196,
    "baseline_violations": 183554,
    "baseline_overlap": 182257,
    "baseline_boundary": 1297,
    "baseline_hpwl": 96391.125,
    "n_offending": 1298,
    "hand_violations": 35429,
    "hand_hpwl": 112636.4375,
    "t_hand": 2.6928656101226807,
    "neural_violations": null,
    "neural_hpwl": null,
    "t_neural": null,
    "hand_improvement": 80.69832310927575
  },
  {
    "circuit": "bigblue3",
    "n_macros": 1298,
    "seed": 300,
    "t_sample": 11.370838165283203,
    "baseline_violations": 213049,
    "baseline_overlap": 211752,
    "baseline_boundary": 1297,
    "baseline_hpwl": 100983.390625,
    "n_offending": 1298,
    "hand_violations": 41771,
    "hand_hpwl": 117228.0546875,
    "t_hand": 7.799839735031128,
    "neural_violations": null,
    "neural_hpwl": null,
    "t_neural": null,
    "hand_improvement": 80.393712244601
  }
]